django_pg_upsert/__init__.py
django_pg_upsert-0.5.0.dist-info/LICENSE
django_pg_upsert-0.5.0.dist-info/WHEEL
django_pg_upsert-0.5.0.dist-info/METADATA
django_pg_upsert-0.5.0.dist-info/RECORD
