Metadata-Version: 2.1
Name: django-pg-upsert
Version: 0.5.0
Summary: Support Postgres native upsert (INSERT ... ON CONFLICT) for django
Author: Semyon Pupkov
Author-email: mail@semyonpupkov.com
Requires-Python: >=3.7
Classifier: Programming Language :: Python :: 3
Classifier: Programming Language :: Python :: 3.10
Classifier: Programming Language :: Python :: 3.7
Classifier: Programming Language :: Python :: 3.8
Classifier: Programming Language :: Python :: 3.9
Requires-Dist: Django (>=2.2)
